{
    "id": "openshift",
    "title": "OpenShift",
    "navItems": [
        {
            "id": "clusters",
            "appId": "openshift",
            "href": "/openshift",
            "title": "Clusters",
            "product": "Red Hat OpenShift Cluster Manager",
            "description": "View, Register, or Create an OpenShift Cluster."
        },
        {
            "id": "releases",
            "appId": "openshift",
            "href": "/openshift/releases",
            "title": "Releases",
            "filterable": false,
            "product": "Red Hat OpenShift Cluster Manager",
            "description": "View general information on the most recent OpenShift Container Platform release versions that you can install."
        },
        {
            "id": "downloads",
            "appId": "openshift",
            "href": "/openshift/downloads",
            "title": "Downloads",
            "filterable": false,
            "product": "Red Hat OpenShift Cluster Manager"
        }
    ]
}
